config.py
crypto.py
manage.py
cliotp/__init__.py
cliotp/hotp.py
cliotp/secret.py
cliotp/totp.py
cliotp/tests/__init__.py
cliotp/tests/test_hotp.py
cliotp/tests/test_totp.py
db/__init__.py
db/models.py
db/migrations/0001_initial.py
db/migrations/0002_account_algorithm_account_digits_account_period.py
db/migrations/0003_alter_account_algorithm.py
db/migrations/0004_group_salt.py
db/migrations/0005_rename_seed_account_encrpyted_seed.py
db/migrations/0006_account_initialization_vector.py
db/migrations/0007_alter_account_encrpyted_seed_and_more.py
db/migrations/0008_rename_encrpyted_seed_account_encrypted_seed.py
db/migrations/__init__.py
cliotp-0.3.1.dist-info/METADATA
cliotp-0.3.1.dist-info/WHEEL
cliotp-0.3.1.dist-info/entry_points.txt
cliotp-0.3.1.dist-info/top_level.txt
cliotp-0.3.1.dist-info/RECORD
