Metadata-Version: 2.4
Name: cliotp
Version: 0.3.1
Summary: Cli tool to manage and generate TOTPs
License-Expression: MIT
Keywords: totp,rfc6238,rfc4226,cli,authenticator
Requires-Python: >=3.10
Requires-Dist: click>=8.1.8
Requires-Dist: cryptography>=45.0.2
Requires-Dist: django>=5.1.6
Requires-Dist: python-dotenv>=1.1.0
Requires-Dist: rich>=13.9.4
Requires-Dist: ruff>=0.9.6
